sdk/__init__.py
sdk/decorators.py
stellr_sdk-0.0.1.dist-info/METADATA
stellr_sdk-0.0.1.dist-info/WHEEL
stellr_sdk-0.0.1.dist-info/top_level.txt
stellr_sdk-0.0.1.dist-info/RECORD
