Metadata-Version: 2.4
Name: stellr-sdk
Version: 0.0.1
Summary: SDK for creating and registering custon Orrin apps
Author: Aidan White
Author-email: ceo@stellr-company.com
Classifier: Programming Language :: Python :: 3
Classifier: License :: OSI Approved :: MIT License
Classifier: Operating System :: OS Independent
Requires-Python: >=3.9
Dynamic: author
Dynamic: author-email
Dynamic: classifier
Dynamic: description
Dynamic: description-content-type
Dynamic: requires-python
Dynamic: summary
